gunicorn_django_canonical_logs/__about__.py
gunicorn_django_canonical_logs/__init__.py
gunicorn_django_canonical_logs/event_context.py
gunicorn_django_canonical_logs/glogging.py
gunicorn_django_canonical_logs/logfmt.py
gunicorn_django_canonical_logs/partial_failure.py
gunicorn_django_canonical_logs/stack_context.py
gunicorn_django_canonical_logs/gunicorn_hooks/__init__.py
gunicorn_django_canonical_logs/gunicorn_hooks/registered_hooks.py
gunicorn_django_canonical_logs/gunicorn_hooks/registry.py
gunicorn_django_canonical_logs/instrumenters/__init__.py
gunicorn_django_canonical_logs/instrumenters/database.py
gunicorn_django_canonical_logs/instrumenters/exception.py
gunicorn_django_canonical_logs/instrumenters/protocol.py
gunicorn_django_canonical_logs/instrumenters/registry.py
gunicorn_django_canonical_logs/instrumenters/request.py
gunicorn_django_canonical_logs/instrumenters/saturation.py
gunicorn_django_canonical_logs/monitors/__init__.py
gunicorn_django_canonical_logs/monitors/saturation.py
gunicorn_django_canonical_logs/monitors/timeout.py
gunicorn_django_canonical_logs-0.0.10.dist-info/METADATA
gunicorn_django_canonical_logs-0.0.10.dist-info/WHEEL
gunicorn_django_canonical_logs-0.0.10.dist-info/licenses/LICENSE.txt
gunicorn_django_canonical_logs-0.0.10.dist-info/RECORD
