Metadata-Version: 2.4
Name: gunicorn-django-canonical-logs
Version: 0.0.10
Summary: Canonical log lines for Django applications using Gunicorn sync workers
Project-URL: Documentation, https://github.com/bradshjg/gunicorn-django-canonical-logs#readme
Project-URL: Issues, https://github.com/bradshjg/gunicorn-django-canonical-logs/issues
Project-URL: Source, https://github.com/bradshjg/gunicorn-django-canonical-logs
Author-email: James Bradshaw <james.g.bradshaw@gmail.com>
License-Expression: MIT
License-File: LICENSE.txt
Classifier: Development Status :: 4 - Beta
Classifier: Programming Language :: Python
Classifier: Programming Language :: Python :: 3.9
Classifier: Programming Language :: Python :: 3.10
Classifier: Programming Language :: Python :: 3.11
Classifier: Programming Language :: Python :: 3.12
Classifier: Programming Language :: Python :: 3.13
Classifier: Programming Language :: Python :: Implementation :: CPython
Requires-Python: >=3.9
Requires-Dist: django
Requires-Dist: gunicorn
Provides-Extra: test
Requires-Dist: coverage-enable-subprocess==1.0; extra == 'test'
Requires-Dist: coverage[toml]~=7.4; extra == 'test'
Requires-Dist: pytest-django~=4.11; extra == 'test'
Requires-Dist: pytest-mock~=3.12; extra == 'test'
Requires-Dist: pytest-randomly~=3.15; extra == 'test'
Requires-Dist: pytest-rerunfailures~=14.0; extra == 'test'
Requires-Dist: pytest-xdist[psutil]~=3.5; extra == 'test'
Requires-Dist: pytest~=8.1; extra == 'test'
Requires-Dist: requests; extra == 'test'
Requires-Dist: whitenoise; extra == 'test'
